<cfprocessingdirective suppresswhitespace="yes" pageencoding="ISO-8859-1">
<cfsilent>
<!--
L10N Resource File
Section: Archives
Locale: English (en)
Find the requested resource by id
-->
</cfsilent>
<cfswitch expression="#ATTRIBUTES.id#">

<cfcase value="archive_wizard">Archive Wizard</cfcase>
<cfcase value="buildarchive">Build CAR File Archive</cfcase>
<cfcase value="deploy_wizard">Deploy Wizard</cfcase>
<cfcase value="archive_and_deploy">Archives and Deployment</cfcase>
<cfcase value="must_have_session_vars">Sorry, but in order to use this application, you must enable session variables.
You may do so by enabling session variables on the "Memory Variables" page.</cfcase>
<cfcase value="archives_pageHeader">Packaging &amp; Deployment &gt; ColdFusion Archives</cfcase>
<cfcase value="previous_cf_archive_files">
Redeploy ColdFusion archive (CAR) files to this server.
Enter the path or browse to the appropriate CAR file to deploy the files to this server and
update the relevant server settings.
</cfcase>
<cfcase value="l10n_deployarchive">Deploy an Existing Archive</cfcase>
<cfcase value="browswServer">Browse Server</cfcase>
<cfcase value="browswServerTip">Browse Server Directory</cfcase>
<cfcase value="deployeArchive">Deploy </cfcase>
<cfcase value="deployeArchiveTip">Deploy Archive</cfcase>
<cfcase value="archive_header">
ColdFusion lets you define applications for organizing work,
archiving files, and migrating and deploying sites. You can create and
store ColdFusion Archive definitions to archive, migrate, or redeploy
applications at a later date.
</cfcase>
<cfcase value="l10n_createarchive">Create archive</cfcase>
<cfcase value="archiveNameRequired">A valid archive name is required</cfcase>
<cfcase value="CreateArchive">Create</cfcase>
<cfcase value="CreateArchiveTip">Create Archive</cfcase>
<cfcase value="l10n_archivename">Archive Name</cfcase>
<cfcase value="l10n_crntarchives">Current Archive Definition List</cfcase>
<cfcase value="actions">Actions</cfcase>
<cfcase value="archivename">Archive Name</cfcase>
<cfcase value="edit_archive_def">Edit Archive Definition</cfcase>
<cfcase value="build_archive">Build Archive</cfcase>
<cfcase value="delete_archive">Delete Archive</cfcase>
<cfcase value="Edit_archive_tip">Edit Archive Information</cfcase>
<cfcase value="Build_archive_tip">Build Archive</cfcase>
<cfcase value="Delete_archive_tip">Delete Archive</cfcase>
<cfcase value="delete_archive_confirmation">Are you sure you want to delete this archive?</cfcase>
<cfcase value="arch_noarch">No Archives have been defined</cfcase>
<cfcase value="archive_info">Archive Information</cfcase>
<cfcase value="application_name">Archive Name</cfcase>
<cfcase value="files_and_directories">Files and Directories</cfcase>
<cfcase value="dirfiles_to_include">Dir/Files to Include</cfcase>
<cfcase value="dirfiles_to_exclude">Dir/Files to Exclude</cfcase>
<cfcase value="cfx_tags">CFX Tags</cfcase>
<cfcase value="directory_mappings">Directory Mappings</cfcase>
<cfcase value="data_sources">Data Sources</cfcase>
<cfcase value="collections">Collections</cfcase>
<cfcase value="EventGateways">Event Gateways</cfcase>
<cfcase value="EventGatewayTypes">Event Gateway Types</cfcase>
<cfcase value="EventGatewaySettings">Event Gateway Settings</cfcase>
<cfcase value="applets">Applets</cfcase>
<cfcase value="scheduled_tasks">Scheduled Tasks</cfcase>
<cfcase value="settings">Settings</cfcase>
<cfcase value="webservices">Web Services</cfcase>
<cfcase value="pre_restore_to_do_list">Pre-Restore To Do List</cfcase>
<cfcase value="post_restore_to_do_list">Post-Restore To Do List</cfcase>
<cfcase value="close_window">Close Window</cfcase>
<cfcase value="archive_information">Archive Information</cfcase>
<cfcase value="name_and_file_location">Assoc. Files/Dirs</cfcase>
<cfcase value="server_settings">Server Settings</cfcase>
<cfcase value="cf_mappings">CF Mappings</cfcase>
<cfcase value="verity_collections">CF Collections</cfcase>
<cfcase value="java_applets">Java Applets</cfcase>
<cfcase value="archive_to_do_list">Archive To Do List</cfcase>
<cfcase value="archive_summary">Archive Summary</cfcase>
<cfcase value="archive_app">Archive Applets</cfcase>
<cfcase value="select_all">Select All</cfcase>
<cfcase value="deselect_all">Deselect All</cfcase>
<cfcase value="l10n_archjavaapp">Registered Java Applets</cfcase>
<cfcase value="name">Name</cfcase>
<cfcase value="code">Code</cfcase>
<cfcase value="path">Path</cfcase>
<cfcase value="l10n_archsum">Archive Summary</cfcase>
<cfcase value="category">Category</cfcase>
<cfcase value="details">Details</cfcase>
<cfcase value="archive_dirmap">Archive ColdFusion Directory Mappings</cfcase>
<cfcase value="l10n_archinclude">Included Files and Directories in Archive</cfcase>
<cfcase value="logical_path">Logical Path</cfcase>
<cfcase value="directory_path">Directory Path</cfcase>
<cfcase value="archive_cfx">Archive CFX</cfcase>
<cfcase value="registeredCFX">Registered CFX Tags</cfcase>
<cfcase value="class_path_or_library_path">Class Path or Library Path</cfcase>
<cfcase value="archive_ds">Archive Data Sources</cfcase>
<cfcase value="l10n_archdata1z1">DSN and Data Source Settings</cfcase>
<cfcase value="driver">Driver</cfcase>
<cfcase value="archive_eventgateways">Event Gateways</cfcase>
<cfcase value="registeredEventGateways">Registered Gateway Instances</cfcase>
<cfcase value="registeredEventGatewaysTypes">Registered Gateway Types</cfcase>
<cfcase value="type">Type</cfcase>
<cfcase value="gatewaySettings">Gateway Settings</cfcase>
<cfcase value="button_cancel">Cancel</cfcase>
<cfcase value="button_apply">Apply</cfcase>
<cfcase value="Archive_File_Browser_pagename">Archive File Browser</cfcase>
<cfcase value="include_exclude_assoc_files_folders">Include/Exclude Associated Files and Directories</cfcase>
<cfcase value="add_path">Add Path</cfcase>
<cfcase value="browse">Browse</cfcase>
<cfcase value="included_paths">Included Paths</cfcase>
<cfcase value="remove_path_from_archive">Remove path from archive</cfcase>
<cfcase value="no_files_have_beed_added_to_this_archive">No files have been added to this archive</cfcase>
<cfcase value="l10n_archexclude">Excluded Files and Directories in Archive</cfcase>
<cfcase value="excluded_paths">Excluded Paths</cfcase>
<cfcase value="remove_path_from_archive_seclusion_list">Remove path from archive seclusion list</cfcase>
<cfcase value="no_files_have_been_excluded_from_this_archive">No files have been excluded from this archive</cfcase>
<cfcase value="description">Description</cfcase>
<cfcase value="description_page_information">
Click Select All to create an archive definition that backs up all objects on your ColdFusion Server. Click Deselect All to create an archive definition that does not archive any objects.
</cfcase>
<cfcase value="archive_set">Archive Settings</cfcase>
<cfcase value="ychbsaarch">You changes have been saved as Archive:</cfcase>
<cfcase value="archive_asb">Archive Schedule Build</cfcase>
<cfcase value="browse_server">Browse Server</cfcase>
<cfcase value="archive_ast">Archive Scheduled Tasks</cfcase>
<cfcase value="l10n_archssched">Registered Scheduled Tasks</cfcase>
<cfcase value="date">Date</cfcase>
<cfcase value="url">URL</cfcase>
<cfcase value="archive_arset">Archive Settings</cfcase>
<cfcase value="l10n_archset">General Server Settings</cfcase>
<cfcase value="server_settings_examples">Examples: limit the number of simultaneously processed requests; timeout requests
after X seconds.  See the Settings section of the ColdFusion Administrator for more
details.</cfcase>
<cfcase value="caching">Caching</cfcase>
<cfcase value="caching_examples">Examples: set template cache size; limit the maximum number of cached queries. See the Caching section
for more details.</cfcase>
<cfcase value="basic_security">Basic Security</cfcase>
<cfcase value="basic_security_examples">Examples: enable and assign ColdFusion Administrator/Studio passwords; restrict use of certain tags. See the
Basic Security section for more details.</cfcase>
<cfcase value="variables">Variables</cfcase>
<cfcase value="variables_examples">Examples: enable client and memory variables. See the Variables section for more details.</cfcase>
<cfcase value="java_jvm">Java and JVM</cfcase>
<cfcase value="java_examples">Examples: specify the JVM location; specify JVM arguments. For more information, see the online Help for the Java &amp; JVM page.</cfcase>
<cfcase value="java_warning"><b>WARNING:</b> The Java settings contain system-specific paths that are used to start ColdFusion. If you deploy these settings to another machine and the paths are invalid, ColdFusion will fail to start.</cfcase>
<cfcase value="locking">Locking</cfcase>
<cfcase value="locking_examples">Examples: specify whether simultaneous access to variables is allowed; configure variable scope lock
settings. See the Locking section for more details.</cfcase>
<cfcase value="logging">Logging</cfcase>
<cfcase value="logging_examples">Examples: set the server administrator e-mail address; log the names of pages that take over a
specified length of time to return. See the Logging section for more details.</cfcase>
<cfcase value="mail">Mail</cfcase>
<cfcase value="mail_examples">Examples: specify the mail server; log all e-mail messages sent by ColdFusion. See the Mail section
 for more details.</cfcase>
<cfcase value="debugging1">Debugging</cfcase>
<cfcase value="debugging_examples">Examples: display the names and values of all CGI, URL, form, and cookie variables; display
detailed processing time; See the Debugging section for more details.</cfcase>
<cfcase value="debugging">Charting</cfcase>
<cfcase value="charting_examples">Examples: How many charts to cache,  maximum number of charting threads, cache location, type of cache</cfcase>
<cfcase value="customtagpaths">Custom Tag Paths</cfcase>
<cfcase value="customtagpaths_examples">Examples: The custom tag path settings</cfcase>
<cfcase value="watcher">Watcher Settings</cfcase>
<cfcase value="watcher_examples">Examples: Causes ColdFusion to watch its configuration files and automatically reload them if they change.</cfcase>
<cfcase value="monitoring">Server Monitor Settings</cfcase>
<cfcase value="monitoring_examples">Examples: Server monitor Settings</cfcase>
<cfcase value="probe">System Probes</cfcase>
<cfcase value="probe_examples">Examples: System probes can monitor the health of a web application by checking the contents of a URL at a regular interval</cfcase>
<cfcase value="archive_tdlist">Archive To Do List</cfcase>
<cfcase value="l10n_archpre">Pre-restore List</cfcase>
<cfcase value="l10n_archpost">Post-restore List</cfcase>
<cfcase value="archive_avc">Archive Verity Collection</cfcase>
<cfcase value="l10n_archdata">Registered Verity Collections</cfcase>
<cfcase value="collection_directory">Collection Directory</cfcase>
<cfcase value="l10n_solrarchdata">Registered Solr Collections</cfcase>
<cfcase value="archive_webservices">Archive Web Services</cfcase>
<cfcase value="registeredweb">Registered Web Services</cfcase>
<cfcase value="webservicename">Web Service Name</cfcase>
<cfcase value="wsdlurl">WSDL URL</cfcase>
<cfcase value="back">Back</cfcase>
<cfcase value="next">Next</cfcase>
<cfcase value="close">Close</cfcase>
<cfcase value="pick_archive_file">Archive Location</cfcase>
<cfcase value="build_status">Build Status</cfcase>
<cfcase value="buildWizard_status_pagetitle">Build Status Log</cfcase>
<cfcase value="buildSuccessful">Build Successful</cfcase>
<cfcase value="buildReadLogTimeout">Reading the log file has timed out. \nThis doesn't mean there is an error. \nPlease check the archive log file to verify build process finished.</cfcase>
<cfcase value="buildWizard_pickfile_pagetitle">Archive File Location</cfcase>
<cfcase value="pickcarLocation">Choose Archive File Location</cfcase>
<cfcase value="buildarchive_pickfile_description">
Select or enter the path and file name (with a .car extension) to use for this archive.<br />
Note: If this file already exists, it will be overwritten.
</cfcase>
<cfcase value="buildWizard_summary_pagetitle">Archive Summary</cfcase>
<cfcase value="bkbtndw">Back</cfcase>
<cfcase value="nxbtndw">Next</cfcase>
<cfcase value="clsbtndw">Close</cfcase>
<cfcase value="l10n_deploysum">Archive Summary</cfcase>
<cfcase value="l10n_deployloc">Deploy Location</cfcase>
<cfcase value="l10n_deploystat">Deploy Status</cfcase>
<cfcase value="deployWizard_status_pagetitle">Deploy Status Log</cfcase>
<cfcase value="DeploySuccessful">Deploy Successful</cfcase>
<cfcase value="Deploy_Archive">Deploy Archive</cfcase>
<cfcase value="l10n_deplfiletitle">Select Archive to Deploy on this Server</cfcase>
<cfcase value="l10n_deplfile">
To restore an archive, specify the retrieval method 
(Local, HTTP, or FTP), the current location of the 
archive (.car) file, and the destination for the .car file. </cfcase>
<cfcase value="pageName">Deploy Location</cfcase>
<cfcase value="pickLocationInstructions">Deploy Locations</cfcase>
<cfcase value="l10n_depldirpath">Directory Path Translation</cfcase>
<cfcase value="deploy">Deploy</cfcase>
<cfcase value="ar_sev">Severity</cfcase>
<cfcase value="ar_dat">Date</cfcase>
<cfcase value="ar_tim">Time</cfcase>
<cfcase value="ar_mes">Message</cfcase>
<cfcase value="archive_error_deploy">
Archive file must be a valid archive (.car extension)<br />
</cfcase>
<cfcase value="archive_error_create">
Invalid archive name.  Archive names can only contain letters, numbers, dots, underscores and dashes.
</cfcase>
<cfcase value="buildWithErrors">Build completed with errors, \nPlease check logs for more information </cfcase>
<cfcase value="carFileName_error">
Invalid archive name. Please make sure that a file with a .car extension is defined.<br />
</cfcase>
<cfcase value="DeployWithErrors">Deploy completed with errors, \nPlease check logs for more information </cfcase>

<cfdefaultcase><cfset bSuccess="false"/></cfdefaultcase>
</cfswitch>
</cfprocessingdirective>

